Metadata-Version: 2.4
Name: llama-index-callbacks-wandb
Version: 0.4.1
Summary: llama-index callbacks wandb integration
Author-email: Your Name <you@example.com>
License-Expression: MIT
License-File: LICENSE
Requires-Python: <4.0,>=3.9
Requires-Dist: llama-index-core<0.15,>=0.13.0
Requires-Dist: wandb<0.17,>=0.16.2
